sRemo/__init__.py
sRemo/sRemoAPI.py
sRemo-1.0.0.dist-info/LICENSE
sRemo-1.0.0.dist-info/METADATA
sRemo-1.0.0.dist-info/WHEEL
sRemo-1.0.0.dist-info/top_level.txt
sRemo-1.0.0.dist-info/RECORD
