Metadata-Version: 2.1
Name: sRemo
Version: 1.0.0
Summary: Python client for sRemo(sCloud) API
Home-page: https://github.com/zunda-pixel/sRemo
Author: zunda(@zunda_pixel)
Author-email: zunda.pixel@gmail.com
License: MIT
Platform: UNKNOWN
